xhap/__init__.py
xhap/browser.py
xhap/cli.py
xhap/hap_client.py
xhap/home_client.py
xhap/model.py
xhap/ws_client.py
xhap-0.0.1.dist-info/METADATA
xhap-0.0.1.dist-info/WHEEL
xhap-0.0.1.dist-info/entry_points.txt
xhap-0.0.1.dist-info/licenses/LICENSE
xhap-0.0.1.dist-info/RECORD
