Metadata-Version: 2.3
Name: xhap
Version: 0.0.1
Summary: MXCHIP Home Access Protocol
Project-URL: Homepage, https://www.mxchip.com/
Project-URL: Documentation, https://www.mxchip.com/
Project-URL: Repository, https://www.mxchip.com/
Project-URL: Changelog, https://www.mxchip.com/
Author-email: Snow Yang <yangsw@mxchip.com>
Maintainer-email: Snow Yang <yangsw@mxchip.com>
License: Copyright (c) 2018 The Python Packaging Authority
License-File: LICENSE
Keywords: MXCHIP,mxchip
Classifier: Development Status :: 4 - Beta
Classifier: License :: OSI Approved :: MIT License
Classifier: Programming Language :: Python :: 3
Requires-Python: >=3.10
Requires-Dist: click
Requires-Dist: cryptography
Requires-Dist: rich
Requires-Dist: zeroconf
